fini/__init__.py
fini/_config.py
fini/_config_test.py
fini/_files.py
fini/_files_test.py
fini/main_argparse.py
fini/edit/__init__.py
fini/edit/_edit.py
fini/rollover/__init__.py
fini/rollover/_rollover.py
fini/rollover/_rollover_test.py
fini/rollover/test_data/complex/expected_out.md
fini/rollover/test_data/complex/in.md
fini/rollover/test_data/empty_lines/expected_out.md
fini/rollover/test_data/empty_lines/in.md
fini/rollover/test_data/headers/expected_out.md
fini/rollover/test_data/headers/in.md
fini/rollover/test_data/list_formats/expected_out.md
fini/rollover/test_data/list_formats/in.md
fini/rollover/test_data/multiline_paragraph/expected_out.md
fini/rollover/test_data/multiline_paragraph/in.md
fini/rollover/test_data/nested_lists/expected_out.md
fini/rollover/test_data/nested_lists/in.md
fini/rollover/test_data/one_todo/expected_out.md
fini/rollover/test_data/one_todo/in.md
fini/rollover/test_data/plain_text/expected_out.md
fini/rollover/test_data/plain_text/in.md
fini/rollover/test_data/some_done/expected_out.md
fini/rollover/test_data/some_done/in.md
fini/sync/__init__.py
fini/sync/_sync.py
fini/sync/_sync_test.py
fini-0.2.0.dist-info/METADATA
fini-0.2.0.dist-info/WHEEL
fini-0.2.0.dist-info/entry_points.txt
fini-0.2.0.dist-info/licenses/LICENSE.txt
fini-0.2.0.dist-info/RECORD
