Metadata-Version: 2.4
Name: fini
Version: 0.2.0
Summary: Tiny CLI for hard working ants
Author-email: alexjuda <alexanderjuda@gmail.com>
License-Expression: Apache-2.0
License-File: LICENSE.txt
Requires-Python: >=3.11
Requires-Dist: gitpython>=3.1.44
